cybuddy/__init__.py
cybuddy/__main__.py
cybuddy/cli.py
cybuddy/config.py
cybuddy/data.py
cybuddy/engine.py
cybuddy/errors.py
cybuddy/formatters.py
cybuddy/handlers.py
cybuddy/history.py
cybuddy/nl_parser.py
cybuddy/suggestions.py
cybuddy/tui.py
cybuddy/commands/__init__.py
cybuddy/commands/history.py
cybuddy/tui/__init__.py
cybuddy/tui/logo.py
cybuddy/tui/simple.py
cybuddy/tui/core/__init__.py
cybuddy/tui/core/events.py
cybuddy/tui/core/history.py
cybuddy/tui/core/scheduler.py
cybuddy/tui/core/terminal.py
cybuddy/tui/overlays/__init__.py
cybuddy/tui/overlays/base.py
cybuddy/tui/overlays/pager.py
cybuddy-1.1.2.dist-info/licenses/LICENSE
cybuddy-1.1.2.dist-info/METADATA
cybuddy-1.1.2.dist-info/WHEEL
cybuddy-1.1.2.dist-info/entry_points.txt
cybuddy-1.1.2.dist-info/top_level.txt
cybuddy-1.1.2.dist-info/RECORD
