Metadata-Version: 2.4
Name: cybuddy
Version: 1.1.2
Summary: Smart Cybersecurity learning assistant
Author: Cybuddy Team
License-Expression: MIT
Project-URL: Homepage, https://github.com/cyguidesltd/cybuddy
Project-URL: Documentation, https://github.com/cyguidesltd/cybuddy#readme
Project-URL: Issues, https://github.com/cyguidesltd/cybuddy/issues
Project-URL: Source, https://github.com/cyguidesltd/cybuddy
Keywords: cybersecurity,learning,pentesting,security,cli,tui
Classifier: Development Status :: 5 - Production/Stable
Classifier: Intended Audience :: Education
Classifier: Intended Audience :: Information Technology
Classifier: Programming Language :: Python :: 3
Classifier: Programming Language :: Python :: 3.10
Classifier: Programming Language :: Python :: 3.11
Classifier: Programming Language :: Python :: 3.12
Classifier: Topic :: Security
Classifier: Topic :: Education
Classifier: Topic :: System :: Networking
Requires-Python: >=3.10
License-File: LICENSE
Requires-Dist: prompt-toolkit>=3.0
Requires-Dist: rich>=13.7
Requires-Dist: pyyaml>=6.0
Provides-Extra: dev
Requires-Dist: pytest>=7.4; extra == "dev"
Requires-Dist: pytest-cov>=4.1; extra == "dev"
Requires-Dist: ruff>=0.6.9; extra == "dev"
Requires-Dist: mypy>=1.11; extra == "dev"
Requires-Dist: types-setuptools; extra == "dev"
Dynamic: license-file
